[
  {
    "username": "Premshaw23",
    "name": "Prem Shaw",
    "admin": true,
    "contributions": 808
  },
  {
    "username": "Prateek2007-cmd",
    "contributions": 40
  },
  {
    "username": "Hrithik-ui753",
    "contributions": 34
  },
  {
    "username": "RUSHILPATEL33",
    "contributions": 33
  },
  {
    "username": "mrdeyroy",
    "contributions": 28
  },
  {
    "username": "Pratyush-Panda-2006",
    "contributions": 27
  },
  {
    "username": "Vaishnav-Hub9",
    "contributions": 24
  },
  {
    "username": "sricharan-213",
    "contributions": 24
  },
  {
    "username": "leno23",
    "contributions": 20
  },
  {
    "username": "pithva007",
    "contributions": 18
  },
  {
    "username": "PRODHOSH",
    "contributions": 17
  },
  {
    "username": "pranav-cholleti",
    "contributions": 17
  },
  {
    "username": "omnipotentchaos",
    "contributions": 16
  },
  {
    "username": "Aditya8369",
    "contributions": 14
  },
  {
    "username": "harshbok69-bit",
    "contributions": 13
  },
  {
    "username": "Siddh2024",
    "contributions": 13
  },
  {
    "username": "pragya0129",
    "contributions": 12
  },
  {
    "username": "Sandeep6135",
    "contributions": 11
  },
  {
    "username": "Divyanshu227",
    "contributions": 10
  },
  {
    "username": "NiranjanDoijode23",
    "contributions": 10
  },
  {
    "username": "nivedha2025cse-gif",
    "contributions": 10
  },
  {
    "username": "paripnj",
    "contributions": 10
  },
  {
    "username": "thevaibhavtyagi",
    "contributions": 9
  },
  {
    "username": "vaishnavijha12",
    "contributions": 9
  },
  {
    "username": "advikdivekar",
    "contributions": 8
  },
  {
    "username": "nimkarprachi17",
    "contributions": 7
  },
  {
    "username": "AdityaNarayanPadhi",
    "contributions": 7
  },
  {
    "username": "yuvraj-k-singh",
    "contributions": 6
  },
  {
    "username": "varun29sharma",
    "contributions": 6
  },
  {
    "username": "HarshaNaidu11",
    "contributions": 6
  },
  {
    "username": "Nihal-Reddy-K",
    "contributions": 6
  },
  {
    "username": "udaycodespace",
    "contributions": 5
  },
  {
    "username": "pericharlabindhumadhavi-data",
    "contributions": 5
  },
  {
    "username": "zairahussain27",
    "contributions": 5
  },
  {
    "username": "Vikrant0207",
    "contributions": 5
  },
  {
    "username": "KRUSHAL2956",
    "contributions": 4
  },
  {
    "username": "priyanshi-coder-2",
    "contributions": 4
  },
  {
    "username": "SuhridXSingh",
    "contributions": 4
  },
  {
    "username": "Copilot",
    "contributions": 4
  },
  {
    "username": "anshika1179",
    "contributions": 4
  },
  {
    "username": "vedant7007",
    "contributions": 4
  },
  {
    "username": "Shanidhya01",
    "contributions": 4
  },
  {
    "username": "shauryaparth1902-blip",
    "contributions": 3
  },
  {
    "username": "Rajal-ui",
    "contributions": 3
  },
  {
    "username": "tanishrajh",
    "contributions": 3
  },
  {
    "username": "vaishalig03",
    "contributions": 3
  },
  {
    "username": "Tanish-Solanki",
    "contributions": 3
  },
  {
    "username": "ssuyashhhh",
    "contributions": 3
  },
  {
    "username": "Pratikshya32",
    "contributions": 3
  },
  {
    "username": "Prashantbhati7",
    "contributions": 3
  },
  {
    "username": "Nazia012",
    "contributions": 3
  },
  {
    "username": "Asifmd45",
    "contributions": 3
  },
  {
    "username": "khushi897920-lang",
    "contributions": 3
  },
  {
    "username": "ishitaajain22-tech",
    "contributions": 3
  },
  {
    "username": "hitdepani",
    "contributions": 3
  },
  {
    "username": "atul-upadhyay-7",
    "contributions": 3
  },
  {
    "username": "anujsharma8d",
    "contributions": 3
  },
  {
    "username": "AdityaSekharDas",
    "contributions": 3
  },
  {
    "username": "Smrithi-krishna",
    "contributions": 2
  },
  {
    "username": "Subham503",
    "contributions": 2
  },
  {
    "username": "codedbydollys10",
    "contributions": 2
  },
  {
    "username": "dhiraj-dev-19",
    "contributions": 2
  },
  {
    "username": "Kritika200520",
    "contributions": 2
  },
  {
    "username": "riddhimagupta2",
    "contributions": 2
  },
  {
    "username": "sujal-rana58",
    "contributions": 2
  },
  {
    "username": "vansh-09",
    "contributions": 2
  },
  {
    "username": "Sha-lini3",
    "contributions": 2
  },
  {
    "username": "Shayan-Bhowmik",
    "contributions": 2
  },
  {
    "username": "Nirmai-06",
    "contributions": 2
  },
  {
    "username": "kannatinaveena",
    "contributions": 2
  },
  {
    "username": "KhushiYadav-26",
    "contributions": 2
  },
  {
    "username": "Ketandora",
    "contributions": 2
  },
  {
    "username": "gowthamrdyy",
    "contributions": 2
  },
  {
    "username": "Chakshu-Bamotra",
    "contributions": 2
  },
  {
    "username": "Bhavex",
    "contributions": 2
  },
  {
    "username": "akashgoudsidduluri",
    "contributions": 2
  },
  {
    "username": "adityack477",
    "contributions": 2
  },
  {
    "username": "vikasverma101",
    "contributions": 1
  },
  {
    "username": "PanditG4303",
    "contributions": 1
  },
  {
    "username": "Thejaswini-VS",
    "contributions": 1
  },
  {
    "username": "Tannie02",
    "contributions": 1
  },
  {
    "username": "Sweksha-Kakkar",
    "contributions": 1
  },
  {
    "username": "Srushti-Kamble14",
    "contributions": 1
  },
  {
    "username": "pratyuxxhh",
    "contributions": 1
  },
  {
    "username": "AnxhDarji",
    "contributions": 1
  },
  {
    "username": "karthick7204",
    "contributions": 1
  },
  {
    "username": "mxskaaan",
    "contributions": 1
  },
  {
    "username": "Sagun-Bajpai",
    "contributions": 1
  },
  {
    "username": "sarthakshruti999-code",
    "contributions": 1
  },
  {
    "username": "shambhavivartika06-cmyk",
    "contributions": 1
  },
  {
    "username": "shruti-codes-design",
    "contributions": 1
  },
  {
    "username": "skypank-coder",
    "contributions": 1
  },
  {
    "username": "lover3123",
    "contributions": 1
  },
  {
    "username": "Achiever199",
    "contributions": 1
  },
  {
    "username": "Anshika-Gupta9",
    "contributions": 1
  },
  {
    "username": "ARCHITVARMA15",
    "contributions": 1
  },
  {
    "username": "Hussain053",
    "contributions": 1
  },
  {
    "username": "krishsoni-hub",
    "contributions": 1
  },
  {
    "username": "Meera2906",
    "contributions": 1
  },
  {
    "username": "NiravaM",
    "contributions": 1
  },
  {
    "username": "Bhavikapatel06",
    "contributions": 1
  },
  {
    "username": "PojashriJM",
    "contributions": 1
  },
  {
    "username": "Pragya005",
    "contributions": 1
  },
  {
    "username": "pritesh-4",
    "contributions": 1
  },
  {
    "username": "Sanjay452656",
    "contributions": 1
  },
  {
    "username": "savniagrawal1701",
    "contributions": 1
  },
  {
    "username": "Shashank-8p",
    "contributions": 1
  },
  {
    "username": "Shrutika-Dahale",
    "contributions": 1
  },
  {
    "username": "ionfwsrijan",
    "contributions": 1
  }
]
